lemniscat/plugin/gitlab/__init__.py
lemniscat/plugin/gitlab/gitLab.py
lemniscat/plugin/gitlab/main.py
lemniscat/plugin/gitlab/plugin.yaml
lemniscat/plugin/gitlab/requirements.txt
lemniscat.plugin.gitlab-0.3.1.dist-info/LICENSE
lemniscat.plugin.gitlab-0.3.1.dist-info/METADATA
lemniscat.plugin.gitlab-0.3.1.dist-info/WHEEL
lemniscat.plugin.gitlab-0.3.1.dist-info/top_level.txt
lemniscat.plugin.gitlab-0.3.1.dist-info/RECORD
