Metadata-Version: 2.1
Name: lemniscat.plugin.gitlab
Version: 0.3.1
Summary: A plugin automates interactions with GitLab
Author-email: David DUBOURG <d.dubourg@gmail.com>
License: MIT
Project-URL: Homepage, https://github.com/lemniscat-devops/lemniscat.plugin.gitlab
Project-URL: Issues, https://github.com/lemniscat-devops/lemniscat.plugin.gitlab/issues
Classifier: Programming Language :: Python :: 3
Classifier: License :: OSI Approved :: MIT License
Classifier: Operating System :: OS Independent
Requires-Python: >=3.10
License-File: LICENSE
Requires-Dist: lemniscat.core >=0.2.1
Requires-Dist: PyYAML ==6.0.1
Requires-Dist: pytz ==2023.3
Requires-Dist: python-gitlab >=4.1.0
